toggltempo/__init__.py
toggltempo/__main__.py
toggltempo-2.1.3.dist-info/METADATA
toggltempo-2.1.3.dist-info/WHEEL
toggltempo-2.1.3.dist-info/entry_points.txt
toggltempo-2.1.3.dist-info/top_level.txt
toggltempo-2.1.3.dist-info/RECORD
